[
  {
    "py/object": "model.group.Group",
    "name": "nameG r9v",
    "header": "headersOD xcs",
    "footer": "footer9fyK3MJ3",
    "id": null
  },
  {
    "py/object": "model.group.Group",
    "name": "nameYKha 4",
    "header": "headercRdPzJEhBSbHfX",
    "footer": "footer5Ur  0W",
    "id": null
  },
  {
    "py/object": "model.group.Group",
    "name": "namepCw",
    "header": "headerlHL5XHAt I",
    "footer": "footerYeoU  4Jx0MB41zk",
    "id": null
  },
  {
    "py/object": "model.group.Group",
    "name": "namek ",
    "header": "headerhg5Czf4Yu YhineB",
    "footer": "footerwPm1",
    "id": null
  }
]